polar_bear/__init__.py
polar_bear/ludwig.py
polar_bear/main.py
polar_bear/version.py
polar_bear-0.0.14.dist-info/LICENSE.txt
polar_bear-0.0.14.dist-info/METADATA
polar_bear-0.0.14.dist-info/WHEEL
polar_bear-0.0.14.dist-info/entry_points.txt
polar_bear-0.0.14.dist-info/top_level.txt
polar_bear-0.0.14.dist-info/RECORD
